game_network/AboutDialog.py
game_network/App.py
game_network/Connect.py
game_network/ConnectDialog.py
game_network/ConnectToDialog.py
game_network/EditConnectionDialog.py
game_network/Helper.py
game_network/LogWindow.py
game_network/MainWindow.py
game_network/__init__.py
game_network/test-app.py
game_network/test-pipe.py
game_network/test.py
game_network-0.1.data/scripts/game_network
game_network-0.1.data/scripts/p2p_network
p2p_network/AboutDialog.py
p2p_network/App.py
p2p_network/Connect.py
p2p_network/ConnectDialog.py
p2p_network/ConnectToDialog.py
p2p_network/EditConnectionDialog.py
p2p_network/Helper.py
p2p_network/LogWindow.py
p2p_network/MainWindow.py
p2p_network/__init__.py
p2p_network/test-app.py
p2p_network/test-pipe.py
p2p_network/test.py
game_network-0.1.dist-info/LICENSE
game_network-0.1.dist-info/METADATA
game_network-0.1.dist-info/WHEEL
game_network-0.1.dist-info/top_level.txt
game_network-0.1.dist-info/RECORD
